{
  "item_type": "plate_chest",
  "item_id": "goodnightsleep:rainbow_chestplate",
  "id": "plate_chest:goodnightsleep:rainbow_chestplate",
  "gear_type": {
    "normal_item_weight": 100,
    "runed_item_weight": 0,
    "unique_item_weight": 0
  },
  "rarity": {
    "min_rarity": 0,
    "max_rarity": 4
  },
  "misc": {
    "only_add_stats_if_loot_drop": false,
    "add_to_loot_drops": false,
    "loot_drop_weight": 1000,
    "can_be_salvaged": true
  },
  "level": {
    "min_level": 44,
    "max_level": 46,
    "level_variance": 0
  },
  "unique": {
    "if_unique_random_up_to_tier": 10,
    "unique_id": ""
  }
}