{
  "id": "pantsthunder0",
  "weight": 10000,
  "rarity": 1,
  "tier": 2,
  "registry": "unique_gear",
  "lang_file_string": "item.mmorpg.uniques.pants.pantsthunder0",
  "lang_file_desc_string": "item.mmorpg.uniques.pants.pantsthunder0.desc",
  "primary_stats": [
	"low_armor_flat",
    "low_dodge_flat"
  ],
  "unique_stats": [
	"very_low_health_flat",
    "high_physical_damage_percent",
    "energy_regen_flat",
    "thunder_resist_flat",
    "nature_resist_flat"
  ],
  "can_get_set": false,
  "requirements": {
    "strength": 0.5
  },
  "gear_type": "plate_pants",
  "item_id": "mmorpg:uniques/pants/pantsthunder0"
}